Metadata-Version: 1.0
Name: zak-distributions
Version: 0.1
Summary: Gaussian and Binomial distributions
Home-page: UNKNOWN
Author: Abdul Razak Husin
Author-email: husinabdulrazak@gmail.com
License: UNKNOWN
Platform: UNKNOWN
